<annotation>
	<folder>TrainingData</folder>
	<filename>126.jpg</filename>
	<path>C:\Users\Ciarán Sheehan\Desktop\fyp\TrainingData\126.jpg</path>
	<source>
		<database>Unknown</database>
	</source>
	<size>
		<width>1049</width>
		<height>698</height>
		<depth>3</depth>
	</size>
	<segmented>0</segmented>
	<object>
		<name>bridge</name>
		<pose>Unspecified</pose>
		<truncated>0</truncated>
		<difficult>0</difficult>
		<bndbox>
			<xmin>27</xmin>
			<ymin>99</ymin>
			<xmax>965</xmax>
			<ymax>155</ymax>
		</bndbox>
	</object>
	<object>
		<name>bridge</name>
		<pose>Unspecified</pose>
		<truncated>0</truncated>
		<difficult>0</difficult>
		<bndbox>
			<xmin>409</xmin>
			<ymin>239</ymin>
			<xmax>654</xmax>
			<ymax>258</ymax>
		</bndbox>
	</object>
</annotation>
